dagster_pagerduty/__init__.py
dagster_pagerduty/resources.py
dagster_pagerduty/version.py
dagster_pagerduty_tests/__init__.py
dagster_pagerduty_tests/test_resources.py
dagster_pagerduty_tests/test_version.py
dagster_pagerduty-2019.6.2.dist-info/METADATA
dagster_pagerduty-2019.6.2.dist-info/WHEEL
dagster_pagerduty-2019.6.2.dist-info/top_level.txt
dagster_pagerduty-2019.6.2.dist-info/RECORD
